what/__init__.py
what/__main__.py
what/cli.py
what/what.py
iwhat-0.2.1.dist-info/LICENSE
iwhat-0.2.1.dist-info/METADATA
iwhat-0.2.1.dist-info/WHEEL
iwhat-0.2.1.dist-info/entry_points.txt
iwhat-0.2.1.dist-info/top_level.txt
iwhat-0.2.1.dist-info/RECORD
